cellartracker/__init__.py
cellartracker/api.py
cellartracker/cellartracker.py
cellartracker/cli.py
cellartracker/client.py
cellartracker/const.py
cellartracker/enum.py
cellartracker/errors.py
cellartracker-1.1.1.dist-info/AUTHORS.rst
cellartracker-1.1.1.dist-info/LICENSE
cellartracker-1.1.1.dist-info/METADATA
cellartracker-1.1.1.dist-info/WHEEL
cellartracker-1.1.1.dist-info/entry_points.txt
cellartracker-1.1.1.dist-info/top_level.txt
cellartracker-1.1.1.dist-info/RECORD
