Metadata-Version: 2.1
Name: cellartracker
Version: 1.1.1
Summary: Python package to export CellarTracker data.
Home-page: https://github.com/mathroule/cellartracker
Author: Mathieu Rul
Author-email: mathroule@gmail.com
License: MIT license
Keywords: cellartracker
Platform: UNKNOWN
Classifier: Development Status :: 5 - Production/Stable
Classifier: Intended Audience :: Developers
Classifier: License :: OSI Approved :: MIT License
Classifier: Natural Language :: English
Classifier: Programming Language :: Python :: 3
Classifier: Programming Language :: Python :: 3.5
Classifier: Programming Language :: Python :: 3.6
Classifier: Programming Language :: Python :: 3.7
Classifier: Programming Language :: Python :: 3.8
Requires-Python: >=3.5
Requires-Dist: requests
